lilliepy_router/__init__.py
lilliepy_router/main.py
lilliepy_router-0.1.0.dist-info/METADATA
lilliepy_router-0.1.0.dist-info/WHEEL
lilliepy_router-0.1.0.dist-info/top_level.txt
lilliepy_router-0.1.0.dist-info/RECORD
